odoo8_addon_invoice_department-8.0.1.0.0.99.dev8-nspkg.pth
odoo_addons/invoice_department/LICENSE
odoo_addons/invoice_department/README.rst
odoo_addons/invoice_department/__init__.py
odoo_addons/invoice_department/__openerp__.py
odoo_addons/invoice_department/i18n/es.po
odoo_addons/invoice_department/models/__init__.py
odoo_addons/invoice_department/models/invoice.py
odoo_addons/invoice_department/report/__init__.py
odoo_addons/invoice_department/report/account_invoice_report.py
odoo_addons/invoice_department/report/account_invoice_report_view.xml
odoo_addons/invoice_department/static/description/icon.png
odoo_addons/invoice_department/views/invoice_view.xml
odoo8_addon_invoice_department-8.0.1.0.0.99.dev8.dist-info/METADATA
odoo8_addon_invoice_department-8.0.1.0.0.99.dev8.dist-info/WHEEL
odoo8_addon_invoice_department-8.0.1.0.0.99.dev8.dist-info/namespace_packages.txt
odoo8_addon_invoice_department-8.0.1.0.0.99.dev8.dist-info/top_level.txt
odoo8_addon_invoice_department-8.0.1.0.0.99.dev8.dist-info/RECORD
